TwoSenses/__init__.py
twoSenses-0.0.2.dist-info/LICENSE.txt
twoSenses-0.0.2.dist-info/METADATA
twoSenses-0.0.2.dist-info/WHEEL
twoSenses-0.0.2.dist-info/top_level.txt
twoSenses-0.0.2.dist-info/RECORD
